task5.py
task5-0.1.0.dist-info/LICENSE.txt
task5-0.1.0.dist-info/WHEEL
task5-0.1.0.dist-info/METADATA
task5-0.1.0.dist-info/RECORD
