Metadata-Version: 2.1
Name: task5
Version: 0.1.0
Summary: task 5
Author: Dmitry
Author-email: kocherzhenko.work@gmail.com
Requires-Python: >=3.10,<4.0
Classifier: Programming Language :: Python :: 3
Classifier: Programming Language :: Python :: 3.10
